simplinear_regression/__init__.py
simplinear_regression/simplinear_regression.py
simplinear_regression-0.1.0.dist-info/License
simplinear_regression-0.1.0.dist-info/METADATA
simplinear_regression-0.1.0.dist-info/WHEEL
simplinear_regression-0.1.0.dist-info/top_level.txt
simplinear_regression-0.1.0.dist-info/RECORD
