Metadata-Version: 2.1
Name: simplinear-regression
Version: 0.1.0
Summary: A simple Linear Regression implementation in pure Python
Author: Md. Ismiel Hossen Abir
Author-email: ismielabir1971@gmail.com
Classifier: Programming Language :: Python :: 3
Classifier: Operating System :: OS Independent
Requires-Python: >=3.6
License-File: License
